idapload/__init__.py
idapload/__main__.py
idapload/argument_parser.py
idapload/clients.py
idapload/core.py
idapload/env.py
idapload/event.py
idapload/exception.py
idapload/inspectidapload.py
idapload/inspectlocust.py
idapload/log.py
idapload/main.py
idapload/runners.py
idapload/stats.py
idapload/wait_time.py
idapload/web.py
idapload/contrib/__init__.py
idapload/contrib/fasthttp.py
idapload/rpc/__init__.py
idapload/rpc/protocol.py
idapload/rpc/zmqrpc.py
idapload/static/.DS_Store
idapload/static/chart.js
idapload/static/echarts.common.min.js
idapload/static/idapload.js
idapload/static/jquery-1.11.3.min.js
idapload/static/jquery.jqote2.min.js
idapload/static/jquery.tools.min.js
idapload/static/locust.js
idapload/static/style.css
idapload/static/vintage.js
idapload/static/img/.DS_Store
idapload/static/img/favicon.ico
idapload/static/img/logo.png
idapload/static/img/top_bg.png
idapload/templates/index.html
idapload/test/__init__.py
idapload/test/mock_locustfile.py
idapload/test/mock_logging.py
idapload/test/test_client.py
idapload/test/test_fasthttp.py
idapload/test/test_locust_class.py
idapload/test/test_main.py
idapload/test/test_old_wait_api.py
idapload/test/test_parser.py
idapload/test/test_runners.py
idapload/test/test_stats.py
idapload/test/test_task_sequence_class.py
idapload/test/test_taskratio.py
idapload/test/test_util.py
idapload/test/test_wait_time.py
idapload/test/test_web.py
idapload/test/test_zmqrpc.py
idapload/test/testcases.py
idapload/util/__init__.py
idapload/util/cache.py
idapload/util/deprecation.py
idapload/util/exception_handler.py
idapload/util/rounding.py
idapload/util/timespan.py
idaploadio-0.15.0.dist-info/LICENSE
idaploadio-0.15.0.dist-info/METADATA
idaploadio-0.15.0.dist-info/WHEEL
idaploadio-0.15.0.dist-info/entry_points.txt
idaploadio-0.15.0.dist-info/top_level.txt
idaploadio-0.15.0.dist-info/RECORD
